MANIFEST.in
README.md
setup.py
django_sn.egg-info/PKG-INFO
django_sn.egg-info/SOURCES.txt
django_sn.egg-info/dependency_links.txt
django_sn.egg-info/not-zip-safe
django_sn.egg-info/requires.txt
django_sn.egg-info/top_level.txt
django_summernote/__init__.py
django_summernote/admin.py
django_summernote/apps.py
django_summernote/fields.py
django_summernote/forms.py
django_summernote/models.py
django_summernote/settings.py
django_summernote/urls.py
django_summernote/utils.py
django_summernote/views.py
django_summernote/widgets.py
django_summernote/migrations/0001_initial.py
django_summernote/migrations/0002_update-help_text.py
django_summernote/migrations/__init__.py
django_summernote/static/summernote/ResizeSensor.js
django_summernote/static/summernote/SOURCE
django_summernote/static/summernote/django_summernote.css
django_summernote/static/summernote/jquery.fileupload.js
django_summernote/static/summernote/jquery.iframe-transport.js
django_summernote/static/summernote/jquery.ui.widget.js
django_summernote/static/summernote/summernote-bs4.css
django_summernote/static/summernote/summernote-bs4.min.js
django_summernote/static/summernote/summernote-lite.css
django_summernote/static/summernote/summernote-lite.min.js
django_summernote/static/summernote/summernote.css
django_summernote/static/summernote/summernote.min.js
django_summernote/static/summernote/summernote.png
django_summernote/static/summernote/font/summernote.eot
django_summernote/static/summernote/font/summernote.ttf
django_summernote/static/summernote/font/summernote.woff
django_summernote/static/summernote/lang/summernote-ar-AR.js
django_summernote/static/summernote/lang/summernote-ar-AR.min.js
django_summernote/static/summernote/lang/summernote-bg-BG.js
django_summernote/static/summernote/lang/summernote-bg-BG.min.js
django_summernote/static/summernote/lang/summernote-ca-ES.js
django_summernote/static/summernote/lang/summernote-ca-ES.min.js
django_summernote/static/summernote/lang/summernote-cs-CZ.js
django_summernote/static/summernote/lang/summernote-cs-CZ.min.js
django_summernote/static/summernote/lang/summernote-da-DK.js
django_summernote/static/summernote/lang/summernote-da-DK.min.js
